AUTHORS
CHANGELOG.txt
DESCRIPTION
LICENSE
MANIFEST.in
README.md
README.rst
requirements.txt
runtests.py
setup.cfg
setup.py
test_requirements.txt
tox.ini
addresses/.env
addresses/__init__.py
addresses/admin.py
addresses/app_settings.py
addresses/apps.py
addresses/compat.py
addresses/filters.py
addresses/forms.py
addresses/managers.py
addresses/models.py
addresses/signals.py
addresses/tables.py
addresses/urls.py
addresses/views.py
addresses/widgets.py
addresses/api/__init__.py
addresses/api/permissions.py
addresses/api/serializers.py
addresses/api/urls.py
addresses/api/views.py
addresses/fixtures/countries.json
addresses/fixtures/states.json
addresses/migrations/0001_initial.py
addresses/migrations/__init__.py
addresses/static/.empty
addresses/static/addresses/.empty
addresses/static/addresses/address/js/address.js
addresses/static/addresses/js/jquery.geocomplete.js
addresses/static/addresses/js/jquery.geocomplete.min.js
addresses/static/addresses/js/geocomplete/jquery.geocomplete.js
addresses/static/addresses/js/geocomplete/jquery.geocomplete.min.js
addresses/templates/addresses/.empty
addresses/templates/addresses/main.html
addresses/templates/addresses/address/form.html
addresses/templates/addresses/address/manage.html
addresses/templates/addresses/address/table/table_actions.html
addresses/templates/addresses/countries/form.html
addresses/templates/addresses/countries/manage.html
addresses/templates/addresses/countries/table/table_actions.html
addresses/templates/addresses/countries/table/table_boolean.html
addresses/templates/addresses/inc/sidebar_menu.html
addresses/templates/addresses/regions/form.html
addresses/templates/addresses/regions/manage.html
addresses/templates/addresses/regions/table/table_actions.html
addresses/templates/addresses/regions/table/table_boolean.html
addresses/templates/addresses/states/form.html
addresses/templates/addresses/states/manage.html
addresses/templates/addresses/states/table/table_actions.html
dj_geocomplete_address.egg-info/PKG-INFO
dj_geocomplete_address.egg-info/SOURCES.txt
dj_geocomplete_address.egg-info/dependency_links.txt
dj_geocomplete_address.egg-info/requires.txt
dj_geocomplete_address.egg-info/top_level.txt