Metadata-Version: 2.1
Name: dj-geocomplete-address
Version: 0.1.5
Summary: An app that allow manage address.
Home-page: https://github.com/amgcorp-tech/dj-geocomplete-address.git
Author: AMG Technologies Corp
Author-email: yarel@amgtechnologiescorp.com
License: The MIT License
Keywords: django,google,addresses,address,countries,localities,regions,postal codes,geocode
Platform: OS Independent
Provides-Extra: dev
License-File: LICENSE
License-File: AUTHORS
